make_help/__init__.py
make_help/__main__.py
make_help/cli.py
make_help-0.1.3.dist-info/entry_points.txt
make_help-0.1.3.dist-info/LICENSE
make_help-0.1.3.dist-info/WHEEL
make_help-0.1.3.dist-info/METADATA
make_help-0.1.3.dist-info/RECORD
